reefinterface/__init__.py
reefinterface/base.py
reefinterface/constants.py
reefinterface/contracts.py
reefinterface/exceptions.py
reefinterface/key.py
reefinterface/types.json
reefinterface/utils/__init__.py
reefinterface/utils/caching.py
reefinterface/utils/hasher.py
reefinterface/utils/ss58.py
test/__init__.py
test/fixtures.py
test/settings.py
test/test_block.py
test/test_contracts.py
test/test_create_extrinsics.py
test/test_helper_functions.py
test/test_init.py
test/test_keypair.py
test/test_query.py
test/test_query_map.py
test/test_ss58.py
test/test_subscriptions.py
test/test_type_registry.py
reef_interface-1.1.0.dist-info/LICENSE
reef_interface-1.1.0.dist-info/METADATA
reef_interface-1.1.0.dist-info/WHEEL
reef_interface-1.1.0.dist-info/top_level.txt
reef_interface-1.1.0.dist-info/RECORD
