Metadata-Version: 2.1
Name: reef-interface
Version: 1.1.0
Summary: Library for interfacing with a Reef node
Home-page: UNKNOWN
Author: Reef Finance
License: UNKNOWN
Keywords: interface reef maldives blockchain rpc
Platform: UNKNOWN
Classifier: Development Status :: 3 - Alpha
Classifier: Intended Audience :: Developers
Classifier: License :: OSI Approved :: Apache Software License
Classifier: Programming Language :: Python :: 3
Classifier: Programming Language :: Python :: 3.6
Classifier: Programming Language :: Python :: 3.7
Classifier: Programming Language :: Python :: 3.8
Classifier: Programming Language :: Python :: 3.9
Requires-Python: >=3.6, <4
Requires-Dist: websocket-client (~=0.58.0)
Requires-Dist: base58 (~=2.0.1)
Requires-Dist: certifi (>=2020.11.8)
Requires-Dist: idna (>=2.8)
Requires-Dist: requests (~=2.25.1)
Requires-Dist: xxhash (>=1.3.0)
Requires-Dist: scalecodec (<=0.11.23,>=0.11.16)
Requires-Dist: py-sr25519-bindings (~=0.1.2)
Requires-Dist: py-ed25519-bindings (~=0.1.2)
Requires-Dist: py-bip39-bindings (~=0.1.6)
Requires-Dist: packaging (~=21.0)
Provides-Extra: test
Requires-Dist: coverage ; extra == 'test'
Requires-Dist: pytest ; extra == 'test'
